inputrules/__init__.py
inputrules-0.0.5.dist-info/LICENSE
inputrules-0.0.5.dist-info/METADATA
inputrules-0.0.5.dist-info/WHEEL
inputrules-0.0.5.dist-info/top_level.txt
inputrules-0.0.5.dist-info/RECORD
