Metadata-Version: 2.1
Name: inputrules
Version: 0.0.5
Summary: A robust Python library for validating and sanitizing input data with predefined rules and filters
Home-page: https://github.com/alvarodeleon/inputrules
Author: Alvaro De Leon
Author-email: info@alvarodeleon.com
Keywords: validation,sanitization,input,forms,json,security,filters
Classifier: Development Status :: 4 - Beta
Classifier: Intended Audience :: Developers
Classifier: License :: OSI Approved :: MIT License
Classifier: Programming Language :: Python :: 3
Classifier: Programming Language :: Python :: 3.6
Classifier: Programming Language :: Python :: 3.7
Classifier: Programming Language :: Python :: 3.8
Classifier: Programming Language :: Python :: 3.9
Classifier: Programming Language :: Python :: 3.10
Classifier: Programming Language :: Python :: 3.11
Classifier: Topic :: Software Development :: Libraries :: Python Modules
Classifier: Topic :: Internet :: WWW/HTTP
Classifier: Topic :: Security
Requires-Python: >=3.6
License-File: LICENSE
